middleman/__init__.py
middleman-0.0.1.dist-info/LICENSE
middleman-0.0.1.dist-info/METADATA
middleman-0.0.1.dist-info/WHEEL
middleman-0.0.1.dist-info/top_level.txt
middleman-0.0.1.dist-info/RECORD
