Metadata-Version: 2.1
Name: middleman
Version: 0.0.1
Summary: Man in the middle proxy
Home-page: UNKNOWN
Author: Koen Woortman
Author-email: koensw@outlook.com
License: MIT
Platform: UNKNOWN
Classifier: Programming Language :: Python :: 3
Classifier: License :: OSI Approved :: MIT License
Classifier: Operating System :: OS Independent
Classifier: Environment :: Console
Classifier: Environment :: Console :: Curses
